[{"model": "propaganda.propaganda", "pk": 1, "fields": {"nombre": "Promo Agosto", "descripcion": "Promo por Mes patrio", "url": "https://www.facebook.com/442347556108263/photos/a.459526434390375.1073741828.442347556108263/459526587723693/?type=3&theater", "habilitado": true}}, {"model": "propaganda.propaganda", "pk": 2, "fields": {"nombre": "Promo Chukuta", "descripcion": "Promo Chukuta", "url": "https://www.facebook.com/442347556108263/photos/a.459526434390375.1073741828.442347556108263/459526411057044/?type=3&theater", "habilitado": true}}]